MANIFEST.in
README.rst
policy-rc.d
setup.py
stopstartup.py
stopstartup.egg-info/PKG-INFO
stopstartup.egg-info/SOURCES.txt
stopstartup.egg-info/dependency_links.txt
stopstartup.egg-info/entry_points.txt
stopstartup.egg-info/requires.txt
stopstartup.egg-info/top_level.txt