Metadata-Version: 1.0
Name: stopstartup
Version: 1.0.3
Summary: Stop services from starting
Home-page: https://github.com/wemash/stopstartup
Author: Kenneth Pullen
Author-email: ken@mash.is
License: UNKNOWN
Keywords: stop services debian install
Platform: UNKNOWN
